pysnmpcollector/__init__.py
pysnmpcollector/client.py
pysnmpcollector-0.0.2.dist-info/METADATA
pysnmpcollector-0.0.2.dist-info/WHEEL
pysnmpcollector-0.0.2.dist-info/top_level.txt
pysnmpcollector-0.0.2.dist-info/RECORD
