Metadata-Version: 2.1
Name: pysnmpcollector
Version: 0.0.2
Summary: SnmpCollector python client
Home-page: https://github.com/steffenschumacher/pysnmpcollectorclient.git
Author: Steffen Schumacher
Author-email: stsmr@vestas.com
License: UNKNOWN
Platform: UNKNOWN
Classifier: Programming Language :: Python :: 3
Classifier: License :: OSI Approved :: MIT License
Classifier: Operating System :: OS Independent
Requires-Dist: requests
